mcp_pubmed/__init__.py
mcp_pubmed/server.py
autocleaneeg_pubmedmcp-1.1.4.dist-info/METADATA
autocleaneeg_pubmedmcp-1.1.4.dist-info/WHEEL
autocleaneeg_pubmedmcp-1.1.4.dist-info/entry_points.txt
autocleaneeg_pubmedmcp-1.1.4.dist-info/licenses/LICENSE
autocleaneeg_pubmedmcp-1.1.4.dist-info/RECORD
