Metadata-Version: 2.4
Name: autocleaneeg-pubmedmcp
Version: 1.1.4
Summary: A Model Context Protocol (MCP) server for PubMed biomedical research database
Project-URL: Homepage, https://github.com/anthropics/claude-code
Project-URL: Documentation, https://github.com/anthropics/claude-code/tree/main/examples/minimal_mcp_pubmed
Project-URL: Repository, https://github.com/anthropics/claude-code.git
Project-URL: Issues, https://github.com/anthropics/claude-code/issues
Author-email: Ernest Pedapati <ernest.pedapati@cchmc.org>
Maintainer-email: Ernest Pedapati <ernest.pedapati@cchmc.org>
License: MIT License
License-File: LICENSE
Keywords: ai,biomedical,claude,mcp,ncbi,pubmed,research
Classifier: Development Status :: 5 - Production/Stable
Classifier: Intended Audience :: Developers
Classifier: Intended Audience :: Science/Research
Classifier: License :: OSI Approved :: MIT License
Classifier: Operating System :: OS Independent
Classifier: Programming Language :: Python :: 3
Classifier: Programming Language :: Python :: 3.10
Classifier: Programming Language :: Python :: 3.11
Classifier: Programming Language :: Python :: 3.12
Classifier: Topic :: Internet :: WWW/HTTP :: Indexing/Search
Classifier: Topic :: Scientific/Engineering :: Bio-Informatics
Classifier: Topic :: Scientific/Engineering :: Medical Science Apps.
Classifier: Topic :: Software Development :: Libraries :: Python Modules
Requires-Python: >=3.10
Requires-Dist: email-validator>=2.0.0
Requires-Dist: httpx>=0.25.0
Requires-Dist: mcp>=1.0.0
Requires-Dist: pydantic>=2.0.0
Provides-Extra: dev
Requires-Dist: black>=23.0.0; extra == 'dev'
Requires-Dist: mypy>=1.0.0; extra == 'dev'
Requires-Dist: pytest-asyncio>=0.21.0; extra == 'dev'
Requires-Dist: pytest>=7.0.0; extra == 'dev'
Requires-Dist: ruff>=0.1.0; extra == 'dev'
